{
 "meta": {
  "product": "WattWindow",
  "version": 1,
  "updated": "2026-07-23T18:22:07.316Z",
  "description": "At-a-glance: current conditions and the best 2-hour window per region."
 },
 "regions": [
  {
   "region": "Eastern England",
   "dno": "A",
   "now": {
    "price": 33.096,
    "carbon": 245,
    "score": 18
   },
   "best2h": {
    "from": "2026-07-24T10:00Z",
    "to": "2026-07-24T12:00Z",
    "avgPrice": 11.58,
    "avgCarbon": 94,
    "score": 97,
    "savingsVsAvgPct": 55
   }
  },
  {
   "region": "East Midlands",
   "dno": "B",
   "now": {
    "price": 31.353,
    "carbon": 205,
    "score": 18
   },
   "best2h": {
    "from": "2026-07-24T12:30Z",
    "to": "2026-07-24T14:30Z",
    "avgPrice": 12.52,
    "avgCarbon": 49,
    "score": 90,
    "savingsVsAvgPct": 49
   }
  },
  {
   "region": "London",
   "dno": "C",
   "now": {
    "price": 31.353,
    "carbon": 201,
    "score": 19
   },
   "best2h": {
    "from": "2026-07-24T10:30Z",
    "to": "2026-07-24T12:30Z",
    "avgPrice": 11.18,
    "avgCarbon": 87,
    "score": 95,
    "savingsVsAvgPct": 54
   }
  },
  {
   "region": "Merseyside & North Wales",
   "dno": "D",
   "now": {
    "price": 34.839,
    "carbon": 44,
    "score": 16
   },
   "best2h": {
    "from": "2026-07-24T11:00Z",
    "to": "2026-07-24T13:00Z",
    "avgPrice": 13.04,
    "avgCarbon": 11,
    "score": 91,
    "savingsVsAvgPct": 52
   }
  },
  {
   "region": "West Midlands",
   "dno": "E",
   "now": {
    "price": 33.096,
    "carbon": 116,
    "score": 18
   },
   "best2h": {
    "from": "2026-07-24T10:30Z",
    "to": "2026-07-24T12:30Z",
    "avgPrice": 11.91,
    "avgCarbon": 16,
    "score": 93,
    "savingsVsAvgPct": 54
   }
  },
  {
   "region": "North East England",
   "dno": "F",
   "now": {
    "price": 33.096,
    "carbon": 17,
    "score": 16
   },
   "best2h": {
    "from": "2026-07-24T10:00Z",
    "to": "2026-07-24T12:00Z",
    "avgPrice": 11.58,
    "avgCarbon": 10,
    "score": 97,
    "savingsVsAvgPct": 55
   }
  },
  {
   "region": "North West England",
   "dno": "G",
   "now": {
    "price": 33.096,
    "carbon": 52,
    "score": 16
   },
   "best2h": {
    "from": "2026-07-24T13:00Z",
    "to": "2026-07-24T15:00Z",
    "avgPrice": 13.61,
    "avgCarbon": 22,
    "score": 84,
    "savingsVsAvgPct": 47
   }
  },
  {
   "region": "Southern England",
   "dno": "H",
   "now": {
    "price": 33.096,
    "carbon": 150,
    "score": 29
   },
   "best2h": {
    "from": "2026-07-24T10:00Z",
    "to": "2026-07-24T12:00Z",
    "avgPrice": 11.58,
    "avgCarbon": 59,
    "score": 97,
    "savingsVsAvgPct": 55
   }
  },
  {
   "region": "South East England",
   "dno": "J",
   "now": {
    "price": 34.839,
    "carbon": 205,
    "score": 19
   },
   "best2h": {
    "from": "2026-07-24T11:00Z",
    "to": "2026-07-24T13:00Z",
    "avgPrice": 13.04,
    "avgCarbon": 91,
    "score": 92,
    "savingsVsAvgPct": 52
   }
  },
  {
   "region": "South Wales",
   "dno": "K",
   "now": {
    "price": 34.839,
    "carbon": 345,
    "score": 26
   },
   "best2h": {
    "from": "2026-07-24T10:30Z",
    "to": "2026-07-24T12:30Z",
    "avgPrice": 12.64,
    "avgCarbon": 47,
    "score": 95,
    "savingsVsAvgPct": 53
   }
  },
  {
   "region": "South West England",
   "dno": "L",
   "now": {
    "price": 36.582,
    "carbon": 248,
    "score": 30
   },
   "best2h": {
    "from": "2026-07-24T10:30Z",
    "to": "2026-07-24T12:30Z",
    "avgPrice": 13.38,
    "avgCarbon": 105,
    "score": 97,
    "savingsVsAvgPct": 53
   }
  },
  {
   "region": "Yorkshire",
   "dno": "M",
   "now": {
    "price": 31.353,
    "carbon": 86,
    "score": 17
   },
   "best2h": {
    "from": "2026-07-24T13:00Z",
    "to": "2026-07-24T15:00Z",
    "avgPrice": 12.79,
    "avgCarbon": 27,
    "score": 90,
    "savingsVsAvgPct": 48
   }
  },
  {
   "region": "South Scotland",
   "dno": "N",
   "now": {
    "price": 33.096,
    "carbon": 1,
    "score": 50
   },
   "best2h": {
    "from": "2026-07-24T10:00Z",
    "to": "2026-07-24T12:00Z",
    "avgPrice": 11.58,
    "avgCarbon": 1,
    "score": 99,
    "savingsVsAvgPct": 55
   }
  },
  {
   "region": "North Scotland",
   "dno": "P",
   "now": {
    "price": 38.325,
    "carbon": 0,
    "score": 49
   },
   "best2h": {
    "from": "2026-07-24T10:00Z",
    "to": "2026-07-24T12:00Z",
    "avgPrice": 13.74,
    "avgCarbon": 0,
    "score": 99,
    "savingsVsAvgPct": 54
   }
  }
 ]
}