{
 "meta": {
  "product": "WattWindow",
  "version": 1,
  "region": "Eastern England",
  "dno": "A",
  "updated": "2026-07-19T12:05:19.777Z",
  "horizonHalfHours": 20,
  "units": {
   "price": "p/kWh inc. VAT (Octopus Agile)",
   "carbon": "gCO2/kWh (forecast)",
   "score": "0-100, higher = better time to draw power"
  },
  "sources": [
   "api.carbonintensity.org.uk",
   "api.octopus.energy (Agile public tariff feed)"
  ],
  "licence": "Free for personal & non-commercial use with attribution. Commercial use requires a licence — see https://kennethmacfadyen-globemaker.github.io/wattwindow/#pricing"
 },
 "current": {
  "from": "2026-07-19T12:00Z",
  "to": "2026-07-19T12:30Z",
  "price": 10.059,
  "carbon": 138,
  "score": 85,
  "label": "excellent",
  "renewablesPct": 63,
  "mix": {
   "biomass": 0.4,
   "coal": 0,
   "imports": 29.9,
   "gas": 7.1,
   "nuclear": 0.1,
   "other": 0,
   "hydro": 0,
   "solar": 41.6,
   "wind": 20.9
  }
 },
 "windows": {
  "1h": {
   "best": {
    "from": "2026-07-19T12:30Z",
    "to": "2026-07-19T13:30Z",
    "avgPrice": 9.27,
    "avgCarbon": 135,
    "score": 95,
    "savingsVsAvgPct": 60
   },
   "cheapest": {
    "from": "2026-07-19T12:30Z",
    "to": "2026-07-19T13:30Z",
    "avgPrice": 9.27,
    "avgCarbon": 135,
    "score": 95,
    "savingsVsAvgPct": 60
   },
   "greenest": {
    "from": "2026-07-19T12:00Z",
    "to": "2026-07-19T13:00Z",
    "avgPrice": 9.46,
    "avgCarbon": 134,
    "score": 93,
    "savingsVsAvgPct": 60
   }
  },
  "2h": {
   "best": {
    "from": "2026-07-19T12:00Z",
    "to": "2026-07-19T14:00Z",
    "avgPrice": 9.48,
    "avgCarbon": 140,
    "score": 90,
    "savingsVsAvgPct": 60
   },
   "cheapest": {
    "from": "2026-07-19T12:30Z",
    "to": "2026-07-19T14:30Z",
    "avgPrice": 9.41,
    "avgCarbon": 143,
    "score": 88,
    "savingsVsAvgPct": 60
   },
   "greenest": {
    "from": "2026-07-19T12:00Z",
    "to": "2026-07-19T14:00Z",
    "avgPrice": 9.48,
    "avgCarbon": 140,
    "score": 90,
    "savingsVsAvgPct": 60
   }
  },
  "3h": {
   "best": {
    "from": "2026-07-19T12:00Z",
    "to": "2026-07-19T15:00Z",
    "avgPrice": 9.68,
    "avgCarbon": 143,
    "score": 86,
    "savingsVsAvgPct": 59
   },
   "cheapest": {
    "from": "2026-07-19T12:00Z",
    "to": "2026-07-19T15:00Z",
    "avgPrice": 9.68,
    "avgCarbon": 143,
    "score": 86,
    "savingsVsAvgPct": 59
   },
   "greenest": {
    "from": "2026-07-19T12:00Z",
    "to": "2026-07-19T15:00Z",
    "avgPrice": 9.68,
    "avgCarbon": 143,
    "score": 86,
    "savingsVsAvgPct": 59
   }
  },
  "4h": {
   "best": {
    "from": "2026-07-19T12:00Z",
    "to": "2026-07-19T16:00Z",
    "avgPrice": 13.95,
    "avgCarbon": 144,
    "score": 79,
    "savingsVsAvgPct": 40
   },
   "cheapest": {
    "from": "2026-07-19T12:00Z",
    "to": "2026-07-19T16:00Z",
    "avgPrice": 13.95,
    "avgCarbon": 144,
    "score": 79,
    "savingsVsAvgPct": 40
   },
   "greenest": {
    "from": "2026-07-19T12:00Z",
    "to": "2026-07-19T16:00Z",
    "avgPrice": 13.95,
    "avgCarbon": 144,
    "score": 79,
    "savingsVsAvgPct": 40
   }
  },
  "6h": {
   "best": {
    "from": "2026-07-19T12:00Z",
    "to": "2026-07-19T18:00Z",
    "avgPrice": 21.15,
    "avgCarbon": 154,
    "score": 57,
    "savingsVsAvgPct": 10
   },
   "cheapest": {
    "from": "2026-07-19T12:00Z",
    "to": "2026-07-19T18:00Z",
    "avgPrice": 21.15,
    "avgCarbon": 154,
    "score": 57,
    "savingsVsAvgPct": 10
   },
   "greenest": {
    "from": "2026-07-19T12:00Z",
    "to": "2026-07-19T18:00Z",
    "avgPrice": 21.15,
    "avgCarbon": 154,
    "score": 57,
    "savingsVsAvgPct": 10
   }
  },
  "8h": {
   "best": {
    "from": "2026-07-19T12:00Z",
    "to": "2026-07-19T20:00Z",
    "avgPrice": 22.55,
    "avgCarbon": 156,
    "score": 54,
    "savingsVsAvgPct": 4
   },
   "cheapest": {
    "from": "2026-07-19T12:00Z",
    "to": "2026-07-19T20:00Z",
    "avgPrice": 22.55,
    "avgCarbon": 156,
    "score": 54,
    "savingsVsAvgPct": 4
   },
   "greenest": {
    "from": "2026-07-19T12:00Z",
    "to": "2026-07-19T20:00Z",
    "avgPrice": 22.55,
    "avgCarbon": 156,
    "score": 54,
    "savingsVsAvgPct": 4
   }
  }
 },
 "series": [
  {
   "from": "2026-07-19T12:00Z",
   "to": "2026-07-19T12:30Z",
   "price": 10.059,
   "carbon": 138,
   "score": 85,
   "label": "excellent"
  },
  {
   "from": "2026-07-19T12:30Z",
   "to": "2026-07-19T13:00Z",
   "price": 8.862,
   "carbon": 129,
   "score": 100,
   "label": "excellent"
  },
  {
   "from": "2026-07-19T13:00Z",
   "to": "2026-07-19T13:30Z",
   "price": 9.681,
   "carbon": 140,
   "score": 89,
   "label": "excellent"
  },
  {
   "from": "2026-07-19T13:30Z",
   "to": "2026-07-19T14:00Z",
   "price": 9.324,
   "carbon": 152,
   "score": 84,
   "label": "excellent"
  },
  {
   "from": "2026-07-19T14:00Z",
   "to": "2026-07-19T14:30Z",
   "price": 9.765,
   "carbon": 152,
   "score": 78,
   "label": "excellent"
  },
  {
   "from": "2026-07-19T14:30Z",
   "to": "2026-07-19T15:00Z",
   "price": 10.4055,
   "carbon": 145,
   "score": 78,
   "label": "excellent"
  },
  {
   "from": "2026-07-19T15:00Z",
   "to": "2026-07-19T15:30Z",
   "price": 25.683,
   "carbon": 146,
   "score": 73,
   "label": "good"
  },
  {
   "from": "2026-07-19T15:30Z",
   "to": "2026-07-19T16:00Z",
   "price": 27.783,
   "carbon": 148,
   "score": 42,
   "label": "fair"
  },
  {
   "from": "2026-07-19T16:00Z",
   "to": "2026-07-19T16:30Z",
   "price": 33.852,
   "carbon": 155,
   "score": 27,
   "label": "poor"
  },
  {
   "from": "2026-07-19T16:30Z",
   "to": "2026-07-19T17:00Z",
   "price": 33.3795,
   "carbon": 169,
   "score": 26,
   "label": "poor"
  },
  {
   "from": "2026-07-19T17:00Z",
   "to": "2026-07-19T17:30Z",
   "price": 37.2645,
   "carbon": 181,
   "score": 7,
   "label": "poor"
  },
  {
   "from": "2026-07-19T17:30Z",
   "to": "2026-07-19T18:00Z",
   "price": 37.7055,
   "carbon": 190,
   "score": 0,
   "label": "poor"
  },
  {
   "from": "2026-07-19T18:00Z",
   "to": "2026-07-19T18:30Z",
   "price": 26.4915,
   "carbon": 172,
   "score": 47,
   "label": "fair"
  },
  {
   "from": "2026-07-19T18:30Z",
   "to": "2026-07-19T19:00Z",
   "price": 26.7435,
   "carbon": 158,
   "score": 47,
   "label": "fair"
  },
  {
   "from": "2026-07-19T19:00Z",
   "to": "2026-07-19T19:30Z",
   "price": 27.0375,
   "carbon": 152,
   "score": 46,
   "label": "fair"
  },
  {
   "from": "2026-07-19T19:30Z",
   "to": "2026-07-19T20:00Z",
   "price": 26.817,
   "carbon": 174,
   "score": 34,
   "label": "poor"
  },
  {
   "from": "2026-07-19T20:00Z",
   "to": "2026-07-19T20:30Z",
   "price": 26.922,
   "carbon": 170,
   "score": 37,
   "label": "fair"
  },
  {
   "from": "2026-07-19T20:30Z",
   "to": "2026-07-19T21:00Z",
   "price": 26.712,
   "carbon": 173,
   "score": 42,
   "label": "fair"
  },
  {
   "from": "2026-07-19T21:00Z",
   "to": "2026-07-19T21:30Z",
   "price": 27.4365,
   "carbon": 180,
   "score": 22,
   "label": "poor"
  },
  {
   "from": "2026-07-19T21:30Z",
   "to": "2026-07-19T22:00Z",
   "price": 26.2605,
   "carbon": 182,
   "score": 40,
   "label": "fair"
  }
 ]
}