{
 "meta": {
  "product": "WattWindow",
  "version": 1,
  "region": "East Midlands",
  "dno": "B",
  "updated": "2026-07-18T20:25:34.503Z",
  "horizonHalfHours": 52,
  "units": {
   "price": "p/kWh inc. VAT (Octopus Agile)",
   "carbon": "gCO2/kWh (forecast)",
   "score": "0-100, higher = better time to draw power"
  },
  "sources": [
   "api.carbonintensity.org.uk",
   "api.octopus.energy (Agile public tariff feed)"
  ],
  "licence": "Free for personal & non-commercial use with attribution. Commercial use requires a licence — see https://kennethmacfadyen-globemaker.github.io/wattwindow/#pricing"
 },
 "current": {
  "from": "2026-07-18T20:00Z",
  "to": "2026-07-18T20:30Z",
  "price": 24.6225,
  "carbon": 73,
  "score": 28,
  "label": "poor",
  "renewablesPct": 48,
  "mix": {
   "biomass": 27.9,
   "coal": 0,
   "imports": 7.7,
   "gas": 10,
   "nuclear": 6.3,
   "other": 0,
   "hydro": 0,
   "solar": 1.3,
   "wind": 46.7
  }
 },
 "windows": {
  "1h": {
   "best": {
    "from": "2026-07-19T10:00Z",
    "to": "2026-07-19T11:00Z",
    "avgPrice": 8.07,
    "avgCarbon": 45,
    "score": 93,
    "savingsVsAvgPct": 55
   },
   "cheapest": {
    "from": "2026-07-19T10:00Z",
    "to": "2026-07-19T11:00Z",
    "avgPrice": 8.07,
    "avgCarbon": 45,
    "score": 93,
    "savingsVsAvgPct": 55
   },
   "greenest": {
    "from": "2026-07-19T13:00Z",
    "to": "2026-07-19T14:00Z",
    "avgPrice": 8.88,
    "avgCarbon": 37,
    "score": 93,
    "savingsVsAvgPct": 50
   }
  },
  "2h": {
   "best": {
    "from": "2026-07-19T12:30Z",
    "to": "2026-07-19T14:30Z",
    "avgPrice": 8.79,
    "avgCarbon": 38,
    "score": 92,
    "savingsVsAvgPct": 51
   },
   "cheapest": {
    "from": "2026-07-19T09:30Z",
    "to": "2026-07-19T11:30Z",
    "avgPrice": 8.61,
    "avgCarbon": 46,
    "score": 87,
    "savingsVsAvgPct": 52
   },
   "greenest": {
    "from": "2026-07-19T12:00Z",
    "to": "2026-07-19T14:00Z",
    "avgPrice": 8.86,
    "avgCarbon": 37,
    "score": 92,
    "savingsVsAvgPct": 50
   }
  },
  "3h": {
   "best": {
    "from": "2026-07-19T11:30Z",
    "to": "2026-07-19T14:30Z",
    "avgPrice": 9.02,
    "avgCarbon": 38,
    "score": 90,
    "savingsVsAvgPct": 49
   },
   "cheapest": {
    "from": "2026-07-19T10:00Z",
    "to": "2026-07-19T13:00Z",
    "avgPrice": 8.71,
    "avgCarbon": 42,
    "score": 89,
    "savingsVsAvgPct": 51
   },
   "greenest": {
    "from": "2026-07-19T12:00Z",
    "to": "2026-07-19T15:00Z",
    "avgPrice": 9.06,
    "avgCarbon": 37,
    "score": 90,
    "savingsVsAvgPct": 49
   }
  },
  "4h": {
   "best": {
    "from": "2026-07-19T10:00Z",
    "to": "2026-07-19T14:00Z",
    "avgPrice": 8.75,
    "avgCarbon": 41,
    "score": 90,
    "savingsVsAvgPct": 51
   },
   "cheapest": {
    "from": "2026-07-19T10:00Z",
    "to": "2026-07-19T14:00Z",
    "avgPrice": 8.75,
    "avgCarbon": 41,
    "score": 90,
    "savingsVsAvgPct": 51
   },
   "greenest": {
    "from": "2026-07-19T11:30Z",
    "to": "2026-07-19T15:30Z",
    "avgPrice": 11.24,
    "avgCarbon": 39,
    "score": 82,
    "savingsVsAvgPct": 37
   }
  },
  "6h": {
   "best": {
    "from": "2026-07-19T09:00Z",
    "to": "2026-07-19T15:00Z",
    "avgPrice": 8.96,
    "avgCarbon": 42,
    "score": 87,
    "savingsVsAvgPct": 50
   },
   "cheapest": {
    "from": "2026-07-19T08:30Z",
    "to": "2026-07-19T14:30Z",
    "avgPrice": 8.95,
    "avgCarbon": 43,
    "score": 87,
    "savingsVsAvgPct": 50
   },
   "greenest": {
    "from": "2026-07-19T10:00Z",
    "to": "2026-07-19T16:00Z",
    "avgPrice": 11.91,
    "avgCarbon": 40,
    "score": 81,
    "savingsVsAvgPct": 33
   }
  },
  "8h": {
   "best": {
    "from": "2026-07-19T07:00Z",
    "to": "2026-07-19T15:00Z",
    "avgPrice": 9.15,
    "avgCarbon": 45,
    "score": 83,
    "savingsVsAvgPct": 49
   },
   "cheapest": {
    "from": "2026-07-19T07:00Z",
    "to": "2026-07-19T15:00Z",
    "avgPrice": 9.15,
    "avgCarbon": 45,
    "score": 83,
    "savingsVsAvgPct": 49
   },
   "greenest": {
    "from": "2026-07-19T08:30Z",
    "to": "2026-07-19T16:30Z",
    "avgPrice": 12.81,
    "avgCarbon": 43,
    "score": 77,
    "savingsVsAvgPct": 28
   }
  }
 },
 "series": [
  {
   "from": "2026-07-18T20:00Z",
   "to": "2026-07-18T20:30Z",
   "price": 24.6225,
   "carbon": 73,
   "score": 28,
   "label": "poor"
  },
  {
   "from": "2026-07-18T20:30Z",
   "to": "2026-07-18T21:00Z",
   "price": 24.339,
   "carbon": 75,
   "score": 28,
   "label": "poor"
  },
  {
   "from": "2026-07-18T21:00Z",
   "to": "2026-07-18T21:30Z",
   "price": 24.045,
   "carbon": 75,
   "score": 30,
   "label": "poor"
  },
  {
   "from": "2026-07-18T21:30Z",
   "to": "2026-07-18T22:00Z",
   "price": 24.192,
   "carbon": 74,
   "score": 30,
   "label": "poor"
  },
  {
   "from": "2026-07-18T22:00Z",
   "to": "2026-07-18T22:30Z",
   "price": 22.3965,
   "carbon": 72,
   "score": 34,
   "label": "poor"
  },
  {
   "from": "2026-07-18T22:30Z",
   "to": "2026-07-18T23:00Z",
   "price": 22.05,
   "carbon": 79,
   "score": 29,
   "label": "poor"
  },
  {
   "from": "2026-07-18T23:00Z",
   "to": "2026-07-18T23:30Z",
   "price": 19.803,
   "carbon": 78,
   "score": 31,
   "label": "poor"
  },
  {
   "from": "2026-07-18T23:30Z",
   "to": "2026-07-19T00:00Z",
   "price": 18.963,
   "carbon": 69,
   "score": 40,
   "label": "fair"
  },
  {
   "from": "2026-07-19T00:00Z",
   "to": "2026-07-19T00:30Z",
   "price": 18.102,
   "carbon": 68,
   "score": 44,
   "label": "fair"
  },
  {
   "from": "2026-07-19T00:30Z",
   "to": "2026-07-19T01:00Z",
   "price": 17.598,
   "carbon": 67,
   "score": 49,
   "label": "fair"
  },
  {
   "from": "2026-07-19T01:00Z",
   "to": "2026-07-19T01:30Z",
   "price": 17.934,
   "carbon": 69,
   "score": 43,
   "label": "fair"
  },
  {
   "from": "2026-07-19T01:30Z",
   "to": "2026-07-19T02:00Z",
   "price": 17.913,
   "carbon": 69,
   "score": 44,
   "label": "fair"
  },
  {
   "from": "2026-07-19T02:00Z",
   "to": "2026-07-19T02:30Z",
   "price": 17.136,
   "carbon": 66,
   "score": 52,
   "label": "fair"
  },
  {
   "from": "2026-07-19T02:30Z",
   "to": "2026-07-19T03:00Z",
   "price": 16.233,
   "carbon": 65,
   "score": 54,
   "label": "fair"
  },
  {
   "from": "2026-07-19T03:00Z",
   "to": "2026-07-19T03:30Z",
   "price": 15.393,
   "carbon": 67,
   "score": 53,
   "label": "fair"
  },
  {
   "from": "2026-07-19T03:30Z",
   "to": "2026-07-19T04:00Z",
   "price": 15.267,
   "carbon": 68,
   "score": 52,
   "label": "fair"
  },
  {
   "from": "2026-07-19T04:00Z",
   "to": "2026-07-19T04:30Z",
   "price": 13.713,
   "carbon": 68,
   "score": 53,
   "label": "fair"
  },
  {
   "from": "2026-07-19T04:30Z",
   "to": "2026-07-19T05:00Z",
   "price": 12.453,
   "carbon": 71,
   "score": 50,
   "label": "fair"
  },
  {
   "from": "2026-07-19T05:00Z",
   "to": "2026-07-19T05:30Z",
   "price": 10.794,
   "carbon": 66,
   "score": 60,
   "label": "good"
  },
  {
   "from": "2026-07-19T05:30Z",
   "to": "2026-07-19T06:00Z",
   "price": 10.71,
   "carbon": 62,
   "score": 64,
   "label": "good"
  },
  {
   "from": "2026-07-19T06:00Z",
   "to": "2026-07-19T06:30Z",
   "price": 8.673,
   "carbon": 63,
   "score": 80,
   "label": "excellent"
  },
  {
   "from": "2026-07-19T06:30Z",
   "to": "2026-07-19T07:00Z",
   "price": 10.941,
   "carbon": 61,
   "score": 63,
   "label": "good"
  },
  {
   "from": "2026-07-19T07:00Z",
   "to": "2026-07-19T07:30Z",
   "price": 10.017,
   "carbon": 57,
   "score": 69,
   "label": "good"
  },
  {
   "from": "2026-07-19T07:30Z",
   "to": "2026-07-19T08:00Z",
   "price": 9.975,
   "carbon": 58,
   "score": 69,
   "label": "good"
  },
  {
   "from": "2026-07-19T08:00Z",
   "to": "2026-07-19T08:30Z",
   "price": 9.261,
   "carbon": 58,
   "score": 76,
   "label": "excellent"
  },
  {
   "from": "2026-07-19T08:30Z",
   "to": "2026-07-19T09:00Z",
   "price": 9.618,
   "carbon": 51,
   "score": 74,
   "label": "good"
  },
  {
   "from": "2026-07-19T09:00Z",
   "to": "2026-07-19T09:30Z",
   "price": 9.198,
   "carbon": 48,
   "score": 81,
   "label": "excellent"
  },
  {
   "from": "2026-07-19T09:30Z",
   "to": "2026-07-19T10:00Z",
   "price": 9.4605,
   "carbon": 52,
   "score": 75,
   "label": "excellent"
  },
  {
   "from": "2026-07-19T10:00Z",
   "to": "2026-07-19T10:30Z",
   "price": 8.253,
   "carbon": 42,
   "score": 94,
   "label": "excellent"
  },
  {
   "from": "2026-07-19T10:30Z",
   "to": "2026-07-19T11:00Z",
   "price": 7.896,
   "carbon": 47,
   "score": 91,
   "label": "excellent"
  },
  {
   "from": "2026-07-19T11:00Z",
   "to": "2026-07-19T11:30Z",
   "price": 8.841,
   "carbon": 43,
   "score": 88,
   "label": "excellent"
  },
  {
   "from": "2026-07-19T11:30Z",
   "to": "2026-07-19T12:00Z",
   "price": 9.555,
   "carbon": 43,
   "score": 80,
   "label": "excellent"
  },
  {
   "from": "2026-07-19T12:00Z",
   "to": "2026-07-19T12:30Z",
   "price": 9.4185,
   "carbon": 33,
   "score": 88,
   "label": "excellent"
  },
  {
   "from": "2026-07-19T12:30Z",
   "to": "2026-07-19T13:00Z",
   "price": 8.274,
   "carbon": 42,
   "score": 93,
   "label": "excellent"
  },
  {
   "from": "2026-07-19T13:00Z",
   "to": "2026-07-19T13:30Z",
   "price": 9.051,
   "carbon": 36,
   "score": 92,
   "label": "excellent"
  },
  {
   "from": "2026-07-19T13:30Z",
   "to": "2026-07-19T14:00Z",
   "price": 8.715,
   "carbon": 38,
   "score": 93,
   "label": "excellent"
  },
  {
   "from": "2026-07-19T14:00Z",
   "to": "2026-07-19T14:30Z",
   "price": 9.135,
   "carbon": 36,
   "score": 91,
   "label": "excellent"
  },
  {
   "from": "2026-07-19T14:30Z",
   "to": "2026-07-19T15:00Z",
   "price": 9.744,
   "carbon": 39,
   "score": 80,
   "label": "excellent"
  },
  {
   "from": "2026-07-19T15:00Z",
   "to": "2026-07-19T15:30Z",
   "price": 25.998,
   "carbon": 41,
   "score": 42,
   "label": "fair"
  },
  {
   "from": "2026-07-19T15:30Z",
   "to": "2026-07-19T16:00Z",
   "price": 27.993,
   "carbon": 43,
   "score": 38,
   "label": "fair"
  },
  {
   "from": "2026-07-19T16:00Z",
   "to": "2026-07-19T16:30Z",
   "price": 33.768,
   "carbon": 50,
   "score": 32,
   "label": "poor"
  },
  {
   "from": "2026-07-19T16:30Z",
   "to": "2026-07-19T17:00Z",
   "price": 33.327,
   "carbon": 64,
   "score": 26,
   "label": "poor"
  },
  {
   "from": "2026-07-19T17:00Z",
   "to": "2026-07-19T17:30Z",
   "price": 37.023,
   "carbon": 75,
   "score": 11,
   "label": "poor"
  },
  {
   "from": "2026-07-19T17:30Z",
   "to": "2026-07-19T18:00Z",
   "price": 37.443,
   "carbon": 117,
   "score": 6,
   "label": "poor"
  },
  {
   "from": "2026-07-19T18:00Z",
   "to": "2026-07-19T18:30Z",
   "price": 25.0635,
   "carbon": 119,
   "score": 20,
   "label": "poor"
  },
  {
   "from": "2026-07-19T18:30Z",
   "to": "2026-07-19T19:00Z",
   "price": 25.305,
   "carbon": 139,
   "score": 16,
   "label": "poor"
  },
  {
   "from": "2026-07-19T19:00Z",
   "to": "2026-07-19T19:30Z",
   "price": 25.5885,
   "carbon": 155,
   "score": 12,
   "label": "poor"
  },
  {
   "from": "2026-07-19T19:30Z",
   "to": "2026-07-19T20:00Z",
   "price": 25.3785,
   "carbon": 167,
   "score": 14,
   "label": "poor"
  },
  {
   "from": "2026-07-19T20:00Z",
   "to": "2026-07-19T20:30Z",
   "price": 25.473,
   "carbon": 173,
   "score": 12,
   "label": "poor"
  },
  {
   "from": "2026-07-19T20:30Z",
   "to": "2026-07-19T21:00Z",
   "price": 25.2735,
   "carbon": 183,
   "score": 15,
   "label": "poor"
  },
  {
   "from": "2026-07-19T21:00Z",
   "to": "2026-07-19T21:30Z",
   "price": 25.9665,
   "carbon": 193,
   "score": 7,
   "label": "poor"
  },
  {
   "from": "2026-07-19T21:30Z",
   "to": "2026-07-19T22:00Z",
   "price": 24.843,
   "carbon": 186,
   "score": 16,
   "label": "poor"
  }
 ]
}