{
 "meta": {
  "product": "WattWindow",
  "version": 1,
  "region": "West Midlands",
  "dno": "E",
  "updated": "2026-07-19T15:11:06.124Z",
  "horizonHalfHours": 62,
  "units": {
   "price": "p/kWh inc. VAT (Octopus Agile)",
   "carbon": "gCO2/kWh (forecast)",
   "score": "0-100, higher = better time to draw power"
  },
  "sources": [
   "api.carbonintensity.org.uk",
   "api.octopus.energy (Agile public tariff feed)"
  ],
  "licence": "Free for personal & non-commercial use with attribution. Commercial use requires a licence — see https://kennethmacfadyen-globemaker.github.io/wattwindow/#pricing"
 },
 "current": {
  "from": "2026-07-19T15:00Z",
  "to": "2026-07-19T15:30Z",
  "price": 24.633,
  "carbon": 32,
  "score": 77,
  "label": "excellent",
  "renewablesPct": 62,
  "mix": {
   "biomass": 3.2,
   "coal": 0,
   "imports": 5.3,
   "gas": 6.8,
   "nuclear": 22.5,
   "other": 0,
   "hydro": 0,
   "solar": 46.3,
   "wind": 15.9
  }
 },
 "windows": {
  "1h": {
   "best": {
    "from": "2026-07-20T13:00Z",
    "to": "2026-07-20T14:00Z",
    "avgPrice": 21.07,
    "avgCarbon": 45,
    "score": 94,
    "savingsVsAvgPct": 23
   },
   "cheapest": {
    "from": "2026-07-20T13:00Z",
    "to": "2026-07-20T14:00Z",
    "avgPrice": 21.07,
    "avgCarbon": 45,
    "score": 94,
    "savingsVsAvgPct": 23
   },
   "greenest": {
    "from": "2026-07-19T15:00Z",
    "to": "2026-07-19T16:00Z",
    "avgPrice": 25.68,
    "avgCarbon": 36,
    "score": 71,
    "savingsVsAvgPct": 6
   }
  },
  "2h": {
   "best": {
    "from": "2026-07-20T12:00Z",
    "to": "2026-07-20T14:00Z",
    "avgPrice": 21.37,
    "avgCarbon": 42,
    "score": 94,
    "savingsVsAvgPct": 22
   },
   "cheapest": {
    "from": "2026-07-20T12:00Z",
    "to": "2026-07-20T14:00Z",
    "avgPrice": 21.37,
    "avgCarbon": 42,
    "score": 94,
    "savingsVsAvgPct": 22
   },
   "greenest": {
    "from": "2026-07-20T11:30Z",
    "to": "2026-07-20T13:30Z",
    "avgPrice": 21.91,
    "avgCarbon": 41,
    "score": 91,
    "savingsVsAvgPct": 20
   }
  },
  "3h": {
   "best": {
    "from": "2026-07-20T10:30Z",
    "to": "2026-07-20T13:30Z",
    "avgPrice": 21.89,
    "avgCarbon": 42,
    "score": 91,
    "savingsVsAvgPct": 20
   },
   "cheapest": {
    "from": "2026-07-20T09:30Z",
    "to": "2026-07-20T12:30Z",
    "avgPrice": 21.81,
    "avgCarbon": 47,
    "score": 89,
    "savingsVsAvgPct": 20
   },
   "greenest": {
    "from": "2026-07-20T10:30Z",
    "to": "2026-07-20T13:30Z",
    "avgPrice": 21.89,
    "avgCarbon": 42,
    "score": 91,
    "savingsVsAvgPct": 20
   }
  },
  "4h": {
   "best": {
    "from": "2026-07-20T10:00Z",
    "to": "2026-07-20T14:00Z",
    "avgPrice": 21.68,
    "avgCarbon": 44,
    "score": 91,
    "savingsVsAvgPct": 20
   },
   "cheapest": {
    "from": "2026-07-20T10:00Z",
    "to": "2026-07-20T14:00Z",
    "avgPrice": 21.68,
    "avgCarbon": 44,
    "score": 91,
    "savingsVsAvgPct": 20
   },
   "greenest": {
    "from": "2026-07-20T10:30Z",
    "to": "2026-07-20T14:30Z",
    "avgPrice": 21.9,
    "avgCarbon": 43,
    "score": 90,
    "savingsVsAvgPct": 20
   }
  },
  "6h": {
   "best": {
    "from": "2026-07-20T09:00Z",
    "to": "2026-07-20T15:00Z",
    "avgPrice": 22.06,
    "avgCarbon": 51,
    "score": 87,
    "savingsVsAvgPct": 19
   },
   "cheapest": {
    "from": "2026-07-20T09:00Z",
    "to": "2026-07-20T15:00Z",
    "avgPrice": 22.06,
    "avgCarbon": 51,
    "score": 87,
    "savingsVsAvgPct": 19
   },
   "greenest": {
    "from": "2026-07-20T09:30Z",
    "to": "2026-07-20T15:30Z",
    "avgPrice": 23.09,
    "avgCarbon": 48,
    "score": 84,
    "savingsVsAvgPct": 15
   }
  },
  "8h": {
   "best": {
    "from": "2026-07-20T07:30Z",
    "to": "2026-07-20T15:30Z",
    "avgPrice": 23.55,
    "avgCarbon": 64,
    "score": 77,
    "savingsVsAvgPct": 14
   },
   "cheapest": {
    "from": "2026-07-20T07:00Z",
    "to": "2026-07-20T15:00Z",
    "avgPrice": 23,
    "avgCarbon": 69,
    "score": 77,
    "savingsVsAvgPct": 16
   },
   "greenest": {
    "from": "2026-07-20T08:30Z",
    "to": "2026-07-20T16:30Z",
    "avgPrice": 25.08,
    "avgCarbon": 59,
    "score": 75,
    "savingsVsAvgPct": 8
   }
  }
 },
 "series": [
  {
   "from": "2026-07-19T15:00Z",
   "to": "2026-07-19T15:30Z",
   "price": 24.633,
   "carbon": 32,
   "score": 77,
   "label": "excellent"
  },
  {
   "from": "2026-07-19T15:30Z",
   "to": "2026-07-19T16:00Z",
   "price": 26.733,
   "carbon": 40,
   "score": 65,
   "label": "good"
  },
  {
   "from": "2026-07-19T16:00Z",
   "to": "2026-07-19T16:30Z",
   "price": 32.802,
   "carbon": 46,
   "score": 43,
   "label": "fair"
  },
  {
   "from": "2026-07-19T16:30Z",
   "to": "2026-07-19T17:00Z",
   "price": 32.3295,
   "carbon": 53,
   "score": 40,
   "label": "fair"
  },
  {
   "from": "2026-07-19T17:00Z",
   "to": "2026-07-19T17:30Z",
   "price": 36.2145,
   "carbon": 57,
   "score": 36,
   "label": "fair"
  },
  {
   "from": "2026-07-19T17:30Z",
   "to": "2026-07-19T18:00Z",
   "price": 36.6555,
   "carbon": 73,
   "score": 33,
   "label": "poor"
  },
  {
   "from": "2026-07-19T18:00Z",
   "to": "2026-07-19T18:30Z",
   "price": 26.4915,
   "carbon": 88,
   "score": 56,
   "label": "good"
  },
  {
   "from": "2026-07-19T18:30Z",
   "to": "2026-07-19T19:00Z",
   "price": 26.7435,
   "carbon": 116,
   "score": 46,
   "label": "fair"
  },
  {
   "from": "2026-07-19T19:00Z",
   "to": "2026-07-19T19:30Z",
   "price": 27.0375,
   "carbon": 148,
   "score": 35,
   "label": "fair"
  },
  {
   "from": "2026-07-19T19:30Z",
   "to": "2026-07-19T20:00Z",
   "price": 26.817,
   "carbon": 157,
   "score": 34,
   "label": "poor"
  },
  {
   "from": "2026-07-19T20:00Z",
   "to": "2026-07-19T20:30Z",
   "price": 26.922,
   "carbon": 159,
   "score": 32,
   "label": "poor"
  },
  {
   "from": "2026-07-19T20:30Z",
   "to": "2026-07-19T21:00Z",
   "price": 26.712,
   "carbon": 163,
   "score": 32,
   "label": "poor"
  },
  {
   "from": "2026-07-19T21:00Z",
   "to": "2026-07-19T21:30Z",
   "price": 27.4365,
   "carbon": 158,
   "score": 28,
   "label": "poor"
  },
  {
   "from": "2026-07-19T21:30Z",
   "to": "2026-07-19T22:00Z",
   "price": 26.2605,
   "carbon": 162,
   "score": 37,
   "label": "fair"
  },
  {
   "from": "2026-07-19T22:00Z",
   "to": "2026-07-19T22:30Z",
   "price": 28.6755,
   "carbon": 167,
   "score": 21,
   "label": "poor"
  },
  {
   "from": "2026-07-19T22:30Z",
   "to": "2026-07-19T23:00Z",
   "price": 26.439,
   "carbon": 160,
   "score": 38,
   "label": "fair"
  },
  {
   "from": "2026-07-19T23:00Z",
   "to": "2026-07-19T23:30Z",
   "price": 24.633,
   "carbon": 152,
   "score": 50,
   "label": "fair"
  },
  {
   "from": "2026-07-19T23:30Z",
   "to": "2026-07-20T00:00Z",
   "price": 24.5805,
   "carbon": 161,
   "score": 46,
   "label": "fair"
  },
  {
   "from": "2026-07-20T00:00Z",
   "to": "2026-07-20T00:30Z",
   "price": 23.73,
   "carbon": 160,
   "score": 48,
   "label": "fair"
  },
  {
   "from": "2026-07-20T00:30Z",
   "to": "2026-07-20T01:00Z",
   "price": 23.3415,
   "carbon": 153,
   "score": 53,
   "label": "fair"
  },
  {
   "from": "2026-07-20T01:00Z",
   "to": "2026-07-20T01:30Z",
   "price": 22.491,
   "carbon": 138,
   "score": 63,
   "label": "good"
  },
  {
   "from": "2026-07-20T01:30Z",
   "to": "2026-07-20T02:00Z",
   "price": 22.365,
   "carbon": 131,
   "score": 68,
   "label": "good"
  },
  {
   "from": "2026-07-20T02:00Z",
   "to": "2026-07-20T02:30Z",
   "price": 22.323,
   "carbon": 128,
   "score": 70,
   "label": "good"
  },
  {
   "from": "2026-07-20T02:30Z",
   "to": "2026-07-20T03:00Z",
   "price": 21.8925,
   "carbon": 121,
   "score": 72,
   "label": "good"
  },
  {
   "from": "2026-07-20T03:00Z",
   "to": "2026-07-20T03:30Z",
   "price": 23.1525,
   "carbon": 109,
   "score": 68,
   "label": "good"
  },
  {
   "from": "2026-07-20T03:30Z",
   "to": "2026-07-20T04:00Z",
   "price": 22.239,
   "carbon": 109,
   "score": 76,
   "label": "excellent"
  },
  {
   "from": "2026-07-20T04:00Z",
   "to": "2026-07-20T04:30Z",
   "price": 23.2785,
   "carbon": 111,
   "score": 64,
   "label": "good"
  },
  {
   "from": "2026-07-20T04:30Z",
   "to": "2026-07-20T05:00Z",
   "price": 22.9425,
   "carbon": 109,
   "score": 71,
   "label": "good"
  },
  {
   "from": "2026-07-20T05:00Z",
   "to": "2026-07-20T05:30Z",
   "price": 24.7485,
   "carbon": 108,
   "score": 60,
   "label": "good"
  },
  {
   "from": "2026-07-20T05:30Z",
   "to": "2026-07-20T06:00Z",
   "price": 26.124,
   "carbon": 108,
   "score": 56,
   "label": "good"
  },
  {
   "from": "2026-07-20T06:00Z",
   "to": "2026-07-20T06:30Z",
   "price": 27.0795,
   "carbon": 119,
   "score": 40,
   "label": "fair"
  },
  {
   "from": "2026-07-20T06:30Z",
   "to": "2026-07-20T07:00Z",
   "price": 26.544,
   "carbon": 142,
   "score": 41,
   "label": "fair"
  },
  {
   "from": "2026-07-20T07:00Z",
   "to": "2026-07-20T07:30Z",
   "price": 27.1845,
   "carbon": 135,
   "score": 35,
   "label": "fair"
  },
  {
   "from": "2026-07-20T07:30Z",
   "to": "2026-07-20T08:00Z",
   "price": 25.515,
   "carbon": 133,
   "score": 50,
   "label": "fair"
  },
  {
   "from": "2026-07-20T08:00Z",
   "to": "2026-07-20T08:30Z",
   "price": 25.725,
   "carbon": 139,
   "score": 47,
   "label": "fair"
  },
  {
   "from": "2026-07-20T08:30Z",
   "to": "2026-07-20T09:00Z",
   "price": 24.906,
   "carbon": 84,
   "score": 63,
   "label": "good"
  },
  {
   "from": "2026-07-20T09:00Z",
   "to": "2026-07-20T09:30Z",
   "price": 23.6145,
   "carbon": 96,
   "score": 67,
   "label": "good"
  },
  {
   "from": "2026-07-20T09:30Z",
   "to": "2026-07-20T10:00Z",
   "price": 21.4095,
   "carbon": 60,
   "score": 86,
   "label": "excellent"
  },
  {
   "from": "2026-07-20T10:00Z",
   "to": "2026-07-20T10:30Z",
   "price": 21.273,
   "carbon": 52,
   "score": 91,
   "label": "excellent"
  },
  {
   "from": "2026-07-20T10:30Z",
   "to": "2026-07-20T11:00Z",
   "price": 21.252,
   "carbon": 43,
   "score": 96,
   "label": "excellent"
  },
  {
   "from": "2026-07-20T11:00Z",
   "to": "2026-07-20T11:30Z",
   "price": 22.47,
   "carbon": 46,
   "score": 84,
   "label": "excellent"
  },
  {
   "from": "2026-07-20T11:30Z",
   "to": "2026-07-20T12:00Z",
   "price": 22.953,
   "carbon": 41,
   "score": 84,
   "label": "excellent"
  },
  {
   "from": "2026-07-20T12:00Z",
   "to": "2026-07-20T12:30Z",
   "price": 21.4725,
   "carbon": 40,
   "score": 94,
   "label": "excellent"
  },
  {
   "from": "2026-07-20T12:30Z",
   "to": "2026-07-20T13:00Z",
   "price": 21.8715,
   "carbon": 40,
   "score": 93,
   "label": "excellent"
  },
  {
   "from": "2026-07-20T13:00Z",
   "to": "2026-07-20T13:30Z",
   "price": 21.3255,
   "carbon": 44,
   "score": 93,
   "label": "excellent"
  },
  {
   "from": "2026-07-20T13:30Z",
   "to": "2026-07-20T14:00Z",
   "price": 20.811,
   "carbon": 45,
   "score": 95,
   "label": "excellent"
  },
  {
   "from": "2026-07-20T14:00Z",
   "to": "2026-07-20T14:30Z",
   "price": 23.037,
   "carbon": 47,
   "score": 79,
   "label": "excellent"
  },
  {
   "from": "2026-07-20T14:30Z",
   "to": "2026-07-20T15:00Z",
   "price": 23.1735,
   "carbon": 52,
   "score": 76,
   "label": "excellent"
  },
  {
   "from": "2026-07-20T15:00Z",
   "to": "2026-07-20T15:30Z",
   "price": 35.994,
   "carbon": 69,
   "score": 36,
   "label": "fair"
  },
  {
   "from": "2026-07-20T15:30Z",
   "to": "2026-07-20T16:00Z",
   "price": 35.994,
   "carbon": 88,
   "score": 34,
   "label": "poor"
  },
  {
   "from": "2026-07-20T16:00Z",
   "to": "2026-07-20T16:30Z",
   "price": 39.7425,
   "carbon": 101,
   "score": 29,
   "label": "poor"
  },
  {
   "from": "2026-07-20T16:30Z",
   "to": "2026-07-20T17:00Z",
   "price": 41.6325,
   "carbon": 117,
   "score": 22,
   "label": "poor"
  },
  {
   "from": "2026-07-20T17:00Z",
   "to": "2026-07-20T17:30Z",
   "price": 42.084,
   "carbon": 132,
   "score": 18,
   "label": "poor"
  },
  {
   "from": "2026-07-20T17:30Z",
   "to": "2026-07-20T18:00Z",
   "price": 43.5015,
   "carbon": 154,
   "score": 11,
   "label": "poor"
  },
  {
   "from": "2026-07-20T18:00Z",
   "to": "2026-07-20T18:30Z",
   "price": 30.996,
   "carbon": 165,
   "score": 16,
   "label": "poor"
  },
  {
   "from": "2026-07-20T18:30Z",
   "to": "2026-07-20T19:00Z",
   "price": 30.324,
   "carbon": 178,
   "score": 19,
   "label": "poor"
  },
  {
   "from": "2026-07-20T19:00Z",
   "to": "2026-07-20T19:30Z",
   "price": 31.08,
   "carbon": 188,
   "score": 13,
   "label": "poor"
  },
  {
   "from": "2026-07-20T19:30Z",
   "to": "2026-07-20T20:00Z",
   "price": 30.6705,
   "carbon": 200,
   "score": 15,
   "label": "poor"
  },
  {
   "from": "2026-07-20T20:00Z",
   "to": "2026-07-20T20:30Z",
   "price": 30.408,
   "carbon": 204,
   "score": 14,
   "label": "poor"
  },
  {
   "from": "2026-07-20T20:30Z",
   "to": "2026-07-20T21:00Z",
   "price": 30.3135,
   "carbon": 202,
   "score": 17,
   "label": "poor"
  },
  {
   "from": "2026-07-20T21:00Z",
   "to": "2026-07-20T21:30Z",
   "price": 30.828,
   "carbon": 203,
   "score": 12,
   "label": "poor"
  },
  {
   "from": "2026-07-20T21:30Z",
   "to": "2026-07-20T22:00Z",
   "price": 27.216,
   "carbon": 201,
   "score": 21,
   "label": "poor"
  }
 ]
}