{
 "meta": {
  "product": "WattWindow",
  "version": 1,
  "region": "South East England",
  "dno": "J",
  "updated": "2026-07-23T19:58:53.927Z",
  "horizonHalfHours": 53,
  "units": {
   "price": "p/kWh inc. VAT (Octopus Agile)",
   "carbon": "gCO2/kWh (forecast)",
   "score": "0-100, higher = better time to draw power"
  },
  "sources": [
   "api.carbonintensity.org.uk",
   "api.octopus.energy (Agile public tariff feed)"
  ],
  "licence": "Free for personal & non-commercial use with attribution. Commercial use requires a licence — see https://kennethmacfadyen-globemaker.github.io/wattwindow/#pricing"
 },
 "current": {
  "from": "2026-07-23T19:30Z",
  "to": "2026-07-23T20:00Z",
  "price": 35.6475,
  "carbon": 202,
  "score": 11,
  "label": "poor",
  "renewablesPct": 3,
  "mix": {
   "biomass": 0,
   "coal": 0,
   "imports": 58.2,
   "gas": 38.9,
   "nuclear": 0,
   "other": 0,
   "hydro": 0.4,
   "solar": 0.6,
   "wind": 1.9
  }
 },
 "windows": {
  "1h": {
   "best": {
    "from": "2026-07-24T14:00Z",
    "to": "2026-07-24T15:00Z",
    "avgPrice": 13.83,
    "avgCarbon": 86,
    "score": 92,
    "savingsVsAvgPct": 48
   },
   "cheapest": {
    "from": "2026-07-24T10:30Z",
    "to": "2026-07-24T11:30Z",
    "avgPrice": 12.17,
    "avgCarbon": 101,
    "score": 91,
    "savingsVsAvgPct": 54
   },
   "greenest": {
    "from": "2026-07-24T14:00Z",
    "to": "2026-07-24T15:00Z",
    "avgPrice": 13.83,
    "avgCarbon": 86,
    "score": 92,
    "savingsVsAvgPct": 48
   }
  },
  "2h": {
   "best": {
    "from": "2026-07-24T11:00Z",
    "to": "2026-07-24T13:00Z",
    "avgPrice": 13.04,
    "avgCarbon": 92,
    "score": 90,
    "savingsVsAvgPct": 51
   },
   "cheapest": {
    "from": "2026-07-24T10:00Z",
    "to": "2026-07-24T12:00Z",
    "avgPrice": 12.3,
    "avgCarbon": 100,
    "score": 90,
    "savingsVsAvgPct": 54
   },
   "greenest": {
    "from": "2026-07-24T14:00Z",
    "to": "2026-07-24T16:00Z",
    "avgPrice": 20.85,
    "avgCarbon": 87,
    "score": 80,
    "savingsVsAvgPct": 22
   }
  },
  "3h": {
   "best": {
    "from": "2026-07-24T10:00Z",
    "to": "2026-07-24T13:00Z",
    "avgPrice": 12.76,
    "avgCarbon": 96,
    "score": 90,
    "savingsVsAvgPct": 52
   },
   "cheapest": {
    "from": "2026-07-24T10:00Z",
    "to": "2026-07-24T13:00Z",
    "avgPrice": 12.76,
    "avgCarbon": 96,
    "score": 90,
    "savingsVsAvgPct": 52
   },
   "greenest": {
    "from": "2026-07-24T14:00Z",
    "to": "2026-07-24T17:00Z",
    "avgPrice": 25.79,
    "avgCarbon": 87,
    "score": 67,
    "savingsVsAvgPct": 3
   }
  },
  "4h": {
   "best": {
    "from": "2026-07-24T10:30Z",
    "to": "2026-07-24T14:30Z",
    "avgPrice": 13.38,
    "avgCarbon": 92,
    "score": 90,
    "savingsVsAvgPct": 50
   },
   "cheapest": {
    "from": "2026-07-24T10:00Z",
    "to": "2026-07-24T14:00Z",
    "avgPrice": 13.33,
    "avgCarbon": 95,
    "score": 89,
    "savingsVsAvgPct": 50
   },
   "greenest": {
    "from": "2026-07-24T13:00Z",
    "to": "2026-07-24T17:00Z",
    "avgPrice": 23.1,
    "avgCarbon": 88,
    "score": 72,
    "savingsVsAvgPct": 13
   }
  },
  "6h": {
   "best": {
    "from": "2026-07-24T09:00Z",
    "to": "2026-07-24T15:00Z",
    "avgPrice": 13.99,
    "avgCarbon": 96,
    "score": 87,
    "savingsVsAvgPct": 48
   },
   "cheapest": {
    "from": "2026-07-24T09:00Z",
    "to": "2026-07-24T15:00Z",
    "avgPrice": 13.99,
    "avgCarbon": 96,
    "score": 87,
    "savingsVsAvgPct": 48
   },
   "greenest": {
    "from": "2026-07-24T11:00Z",
    "to": "2026-07-24T17:00Z",
    "avgPrice": 19.75,
    "avgCarbon": 89,
    "score": 78,
    "savingsVsAvgPct": 26
   }
  },
  "8h": {
   "best": {
    "from": "2026-07-24T07:30Z",
    "to": "2026-07-24T15:30Z",
    "avgPrice": 16.68,
    "avgCarbon": 101,
    "score": 83,
    "savingsVsAvgPct": 38
   },
   "cheapest": {
    "from": "2026-07-24T07:00Z",
    "to": "2026-07-24T15:00Z",
    "avgPrice": 16.46,
    "avgCarbon": 104,
    "score": 82,
    "savingsVsAvgPct": 38
   },
   "greenest": {
    "from": "2026-07-24T09:00Z",
    "to": "2026-07-24T17:00Z",
    "avgPrice": 18.44,
    "avgCarbon": 94,
    "score": 79,
    "savingsVsAvgPct": 31
   }
  }
 },
 "series": [
  {
   "from": "2026-07-23T19:30Z",
   "to": "2026-07-23T20:00Z",
   "price": 35.6475,
   "carbon": 202,
   "score": 11,
   "label": "poor"
  },
  {
   "from": "2026-07-23T20:00Z",
   "to": "2026-07-23T20:30Z",
   "price": 36.015,
   "carbon": 224,
   "score": 2,
   "label": "poor"
  },
  {
   "from": "2026-07-23T20:30Z",
   "to": "2026-07-23T21:00Z",
   "price": 35.0805,
   "carbon": 216,
   "score": 9,
   "label": "poor"
  },
  {
   "from": "2026-07-23T21:00Z",
   "to": "2026-07-23T21:30Z",
   "price": 33.3585,
   "carbon": 214,
   "score": 14,
   "label": "poor"
  },
  {
   "from": "2026-07-23T21:30Z",
   "to": "2026-07-23T22:00Z",
   "price": 30.912,
   "carbon": 214,
   "score": 23,
   "label": "poor"
  },
  {
   "from": "2026-07-23T22:00Z",
   "to": "2026-07-23T22:30Z",
   "price": 31.0905,
   "carbon": 218,
   "score": 19,
   "label": "poor"
  },
  {
   "from": "2026-07-23T22:30Z",
   "to": "2026-07-23T23:00Z",
   "price": 29.295,
   "carbon": 217,
   "score": 26,
   "label": "poor"
  },
  {
   "from": "2026-07-23T23:00Z",
   "to": "2026-07-23T23:30Z",
   "price": 28.371,
   "carbon": 211,
   "score": 32,
   "label": "poor"
  },
  {
   "from": "2026-07-23T23:30Z",
   "to": "2026-07-24T00:00Z",
   "price": 27.7515,
   "carbon": 207,
   "score": 37,
   "label": "fair"
  },
  {
   "from": "2026-07-24T00:00Z",
   "to": "2026-07-24T00:30Z",
   "price": 26.733,
   "carbon": 193,
   "score": 44,
   "label": "fair"
  },
  {
   "from": "2026-07-24T00:30Z",
   "to": "2026-07-24T01:00Z",
   "price": 25.7145,
   "carbon": 181,
   "score": 51,
   "label": "fair"
  },
  {
   "from": "2026-07-24T01:00Z",
   "to": "2026-07-24T01:30Z",
   "price": 26.754,
   "carbon": 162,
   "score": 49,
   "label": "fair"
  },
  {
   "from": "2026-07-24T01:30Z",
   "to": "2026-07-24T02:00Z",
   "price": 25.725,
   "carbon": 157,
   "score": 52,
   "label": "fair"
  },
  {
   "from": "2026-07-24T02:00Z",
   "to": "2026-07-24T02:30Z",
   "price": 24.948,
   "carbon": 126,
   "score": 63,
   "label": "good"
  },
  {
   "from": "2026-07-24T02:30Z",
   "to": "2026-07-24T03:00Z",
   "price": 24.8955,
   "carbon": 130,
   "score": 62,
   "label": "good"
  },
  {
   "from": "2026-07-24T03:00Z",
   "to": "2026-07-24T03:30Z",
   "price": 27.6045,
   "carbon": 129,
   "score": 55,
   "label": "good"
  },
  {
   "from": "2026-07-24T03:30Z",
   "to": "2026-07-24T04:00Z",
   "price": 27.3315,
   "carbon": 125,
   "score": 58,
   "label": "good"
  },
  {
   "from": "2026-07-24T04:00Z",
   "to": "2026-07-24T04:30Z",
   "price": 30.7545,
   "carbon": 133,
   "score": 41,
   "label": "fair"
  },
  {
   "from": "2026-07-24T04:30Z",
   "to": "2026-07-24T05:00Z",
   "price": 29.799,
   "carbon": 137,
   "score": 42,
   "label": "fair"
  },
  {
   "from": "2026-07-24T05:00Z",
   "to": "2026-07-24T05:30Z",
   "price": 29.274,
   "carbon": 139,
   "score": 44,
   "label": "fair"
  },
  {
   "from": "2026-07-24T05:30Z",
   "to": "2026-07-24T06:00Z",
   "price": 30.0615,
   "carbon": 144,
   "score": 37,
   "label": "fair"
  },
  {
   "from": "2026-07-24T06:00Z",
   "to": "2026-07-24T06:30Z",
   "price": 27.909,
   "carbon": 141,
   "score": 47,
   "label": "fair"
  },
  {
   "from": "2026-07-24T06:30Z",
   "to": "2026-07-24T07:00Z",
   "price": 27.909,
   "carbon": 145,
   "score": 45,
   "label": "fair"
  },
  {
   "from": "2026-07-24T07:00Z",
   "to": "2026-07-24T07:30Z",
   "price": 23.688,
   "carbon": 139,
   "score": 63,
   "label": "good"
  },
  {
   "from": "2026-07-24T07:30Z",
   "to": "2026-07-24T08:00Z",
   "price": 22.89,
   "carbon": 129,
   "score": 68,
   "label": "good"
  },
  {
   "from": "2026-07-24T08:00Z",
   "to": "2026-07-24T08:30Z",
   "price": 24.507,
   "carbon": 123,
   "score": 68,
   "label": "good"
  },
  {
   "from": "2026-07-24T08:30Z",
   "to": "2026-07-24T09:00Z",
   "price": 24.444,
   "carbon": 122,
   "score": 70,
   "label": "good"
  },
  {
   "from": "2026-07-24T09:00Z",
   "to": "2026-07-24T09:30Z",
   "price": 17.3775,
   "carbon": 110,
   "score": 77,
   "label": "excellent"
  },
  {
   "from": "2026-07-24T09:30Z",
   "to": "2026-07-24T10:00Z",
   "price": 16.2435,
   "carbon": 113,
   "score": 76,
   "label": "excellent"
  },
  {
   "from": "2026-07-24T10:00Z",
   "to": "2026-07-24T10:30Z",
   "price": 12.432,
   "carbon": 107,
   "score": 87,
   "label": "excellent"
  },
  {
   "from": "2026-07-24T10:30Z",
   "to": "2026-07-24T11:00Z",
   "price": 11.9805,
   "carbon": 104,
   "score": 91,
   "label": "excellent"
  },
  {
   "from": "2026-07-24T11:00Z",
   "to": "2026-07-24T11:30Z",
   "price": 12.3585,
   "carbon": 98,
   "score": 90,
   "label": "excellent"
  },
  {
   "from": "2026-07-24T11:30Z",
   "to": "2026-07-24T12:00Z",
   "price": 12.4215,
   "carbon": 92,
   "score": 90,
   "label": "excellent"
  },
  {
   "from": "2026-07-24T12:00Z",
   "to": "2026-07-24T12:30Z",
   "price": 13.818,
   "carbon": 91,
   "score": 88,
   "label": "excellent"
  },
  {
   "from": "2026-07-24T12:30Z",
   "to": "2026-07-24T13:00Z",
   "price": 13.566,
   "carbon": 86,
   "score": 93,
   "label": "excellent"
  },
  {
   "from": "2026-07-24T13:00Z",
   "to": "2026-07-24T13:30Z",
   "price": 15.435,
   "carbon": 91,
   "score": 84,
   "label": "excellent"
  },
  {
   "from": "2026-07-24T13:30Z",
   "to": "2026-07-24T14:00Z",
   "price": 14.6055,
   "carbon": 89,
   "score": 87,
   "label": "excellent"
  },
  {
   "from": "2026-07-24T14:00Z",
   "to": "2026-07-24T14:30Z",
   "price": 12.873,
   "carbon": 88,
   "score": 93,
   "label": "excellent"
  },
  {
   "from": "2026-07-24T14:30Z",
   "to": "2026-07-24T15:00Z",
   "price": 14.784,
   "carbon": 84,
   "score": 90,
   "label": "excellent"
  },
  {
   "from": "2026-07-24T15:00Z",
   "to": "2026-07-24T15:30Z",
   "price": 27.111,
   "carbon": 88,
   "score": 72,
   "label": "good"
  },
  {
   "from": "2026-07-24T15:30Z",
   "to": "2026-07-24T16:00Z",
   "price": 28.6125,
   "carbon": 88,
   "score": 64,
   "label": "good"
  },
  {
   "from": "2026-07-24T16:00Z",
   "to": "2026-07-24T16:30Z",
   "price": 35.9625,
   "carbon": 91,
   "score": 38,
   "label": "fair"
  },
  {
   "from": "2026-07-24T16:30Z",
   "to": "2026-07-24T17:00Z",
   "price": 35.427,
   "carbon": 82,
   "score": 46,
   "label": "fair"
  },
  {
   "from": "2026-07-24T17:00Z",
   "to": "2026-07-24T17:30Z",
   "price": 42.9555,
   "carbon": 111,
   "score": 30,
   "label": "poor"
  },
  {
   "from": "2026-07-24T17:30Z",
   "to": "2026-07-24T18:00Z",
   "price": 44.205,
   "carbon": 119,
   "score": 27,
   "label": "poor"
  },
  {
   "from": "2026-07-24T18:00Z",
   "to": "2026-07-24T18:30Z",
   "price": 33.222,
   "carbon": 125,
   "score": 37,
   "label": "fair"
  },
  {
   "from": "2026-07-24T18:30Z",
   "to": "2026-07-24T19:00Z",
   "price": 32.6445,
   "carbon": 142,
   "score": 32,
   "label": "poor"
  },
  {
   "from": "2026-07-24T19:00Z",
   "to": "2026-07-24T19:30Z",
   "price": 32.928,
   "carbon": 166,
   "score": 27,
   "label": "poor"
  },
  {
   "from": "2026-07-24T19:30Z",
   "to": "2026-07-24T20:00Z",
   "price": 32.9385,
   "carbon": 186,
   "score": 24,
   "label": "poor"
  },
  {
   "from": "2026-07-24T20:00Z",
   "to": "2026-07-24T20:30Z",
   "price": 34.377,
   "carbon": 190,
   "score": 17,
   "label": "poor"
  },
  {
   "from": "2026-07-24T20:30Z",
   "to": "2026-07-24T21:00Z",
   "price": 34.104,
   "carbon": 192,
   "score": 17,
   "label": "poor"
  },
  {
   "from": "2026-07-24T21:00Z",
   "to": "2026-07-24T21:30Z",
   "price": 33.2535,
   "carbon": 183,
   "score": 22,
   "label": "poor"
  },
  {
   "from": "2026-07-24T21:30Z",
   "to": "2026-07-24T22:00Z",
   "price": 31.101,
   "carbon": 186,
   "score": 27,
   "label": "poor"
  }
 ]
}