{
 "meta": {
  "product": "WattWindow",
  "version": 1,
  "region": "South West England",
  "dno": "L",
  "updated": "2026-07-21T10:32:25.482Z",
  "horizonHalfHours": 23,
  "units": {
   "price": "p/kWh inc. VAT (Octopus Agile)",
   "carbon": "gCO2/kWh (forecast)",
   "score": "0-100, higher = better time to draw power"
  },
  "sources": [
   "api.carbonintensity.org.uk",
   "api.octopus.energy (Agile public tariff feed)"
  ],
  "licence": "Free for personal & non-commercial use with attribution. Commercial use requires a licence — see https://kennethmacfadyen-globemaker.github.io/wattwindow/#pricing"
 },
 "current": {
  "from": "2026-07-21T10:30Z",
  "to": "2026-07-21T11:00Z",
  "price": 23.7615,
  "carbon": 61,
  "score": 71,
  "label": "good",
  "renewablesPct": 77,
  "mix": {
   "biomass": 0.7,
   "coal": 0,
   "imports": 8,
   "gas": 14,
   "nuclear": 0.4,
   "other": 0,
   "hydro": 0,
   "solar": 75.9,
   "wind": 1
  }
 },
 "windows": {
  "1h": {
   "best": {
    "from": "2026-07-21T12:00Z",
    "to": "2026-07-21T13:00Z",
    "avgPrice": 22.7,
    "avgCarbon": 55,
    "score": 91,
    "savingsVsAvgPct": 22
   },
   "cheapest": {
    "from": "2026-07-21T13:30Z",
    "to": "2026-07-21T14:30Z",
    "avgPrice": 22.2,
    "avgCarbon": 72,
    "score": 87,
    "savingsVsAvgPct": 24
   },
   "greenest": {
    "from": "2026-07-21T11:30Z",
    "to": "2026-07-21T12:30Z",
    "avgPrice": 23.18,
    "avgCarbon": 55,
    "score": 84,
    "savingsVsAvgPct": 20
   }
  },
  "2h": {
   "best": {
    "from": "2026-07-21T12:30Z",
    "to": "2026-07-21T14:30Z",
    "avgPrice": 22.33,
    "avgCarbon": 65,
    "score": 89,
    "savingsVsAvgPct": 23
   },
   "cheapest": {
    "from": "2026-07-21T12:30Z",
    "to": "2026-07-21T14:30Z",
    "avgPrice": 22.33,
    "avgCarbon": 65,
    "score": 89,
    "savingsVsAvgPct": 23
   },
   "greenest": {
    "from": "2026-07-21T11:30Z",
    "to": "2026-07-21T13:30Z",
    "avgPrice": 22.82,
    "avgCarbon": 57,
    "score": 87,
    "savingsVsAvgPct": 22
   }
  },
  "3h": {
   "best": {
    "from": "2026-07-21T11:30Z",
    "to": "2026-07-21T14:30Z",
    "avgPrice": 22.61,
    "avgCarbon": 62,
    "score": 87,
    "savingsVsAvgPct": 22
   },
   "cheapest": {
    "from": "2026-07-21T12:00Z",
    "to": "2026-07-21T15:00Z",
    "avgPrice": 22.49,
    "avgCarbon": 66,
    "score": 86,
    "savingsVsAvgPct": 23
   },
   "greenest": {
    "from": "2026-07-21T10:30Z",
    "to": "2026-07-21T13:30Z",
    "avgPrice": 23.05,
    "avgCarbon": 58,
    "score": 83,
    "savingsVsAvgPct": 21
   }
  },
  "4h": {
   "best": {
    "from": "2026-07-21T11:00Z",
    "to": "2026-07-21T15:00Z",
    "avgPrice": 22.69,
    "avgCarbon": 64,
    "score": 84,
    "savingsVsAvgPct": 22
   },
   "cheapest": {
    "from": "2026-07-21T11:00Z",
    "to": "2026-07-21T15:00Z",
    "avgPrice": 22.69,
    "avgCarbon": 64,
    "score": 84,
    "savingsVsAvgPct": 22
   },
   "greenest": {
    "from": "2026-07-21T10:30Z",
    "to": "2026-07-21T14:30Z",
    "avgPrice": 22.84,
    "avgCarbon": 62,
    "score": 84,
    "savingsVsAvgPct": 22
   }
  },
  "6h": {
   "best": {
    "from": "2026-07-21T10:30Z",
    "to": "2026-07-21T16:30Z",
    "avgPrice": 25.93,
    "avgCarbon": 73,
    "score": 70,
    "savingsVsAvgPct": 11
   },
   "cheapest": {
    "from": "2026-07-21T10:30Z",
    "to": "2026-07-21T16:30Z",
    "avgPrice": 25.93,
    "avgCarbon": 73,
    "score": 70,
    "savingsVsAvgPct": 11
   },
   "greenest": {
    "from": "2026-07-21T10:30Z",
    "to": "2026-07-21T16:30Z",
    "avgPrice": 25.93,
    "avgCarbon": 73,
    "score": 70,
    "savingsVsAvgPct": 11
   }
  },
  "8h": {
   "best": {
    "from": "2026-07-21T10:30Z",
    "to": "2026-07-21T18:30Z",
    "avgPrice": 28.76,
    "avgCarbon": 100,
    "score": 58,
    "savingsVsAvgPct": 1
   },
   "cheapest": {
    "from": "2026-07-21T10:30Z",
    "to": "2026-07-21T18:30Z",
    "avgPrice": 28.76,
    "avgCarbon": 100,
    "score": 58,
    "savingsVsAvgPct": 1
   },
   "greenest": {
    "from": "2026-07-21T10:30Z",
    "to": "2026-07-21T18:30Z",
    "avgPrice": 28.76,
    "avgCarbon": 100,
    "score": 58,
    "savingsVsAvgPct": 1
   }
  }
 },
 "series": [
  {
   "from": "2026-07-21T10:30Z",
   "to": "2026-07-21T11:00Z",
   "price": 23.7615,
   "carbon": 61,
   "score": 71,
   "label": "good"
  },
  {
   "from": "2026-07-21T11:00Z",
   "to": "2026-07-21T11:30Z",
   "price": 23.2995,
   "carbon": 62,
   "score": 75,
   "label": "excellent"
  },
  {
   "from": "2026-07-21T11:30Z",
   "to": "2026-07-21T12:00Z",
   "price": 23.2995,
   "carbon": 57,
   "score": 82,
   "label": "excellent"
  },
  {
   "from": "2026-07-21T12:00Z",
   "to": "2026-07-21T12:30Z",
   "price": 23.058,
   "carbon": 53,
   "score": 86,
   "label": "excellent"
  },
  {
   "from": "2026-07-21T12:30Z",
   "to": "2026-07-21T13:00Z",
   "price": 22.3335,
   "carbon": 57,
   "score": 95,
   "label": "excellent"
  },
  {
   "from": "2026-07-21T13:00Z",
   "to": "2026-07-21T13:30Z",
   "price": 22.575,
   "carbon": 59,
   "score": 86,
   "label": "excellent"
  },
  {
   "from": "2026-07-21T13:30Z",
   "to": "2026-07-21T14:00Z",
   "price": 22.5435,
   "carbon": 72,
   "score": 84,
   "label": "excellent"
  },
  {
   "from": "2026-07-21T14:00Z",
   "to": "2026-07-21T14:30Z",
   "price": 21.8505,
   "carbon": 72,
   "score": 89,
   "label": "excellent"
  },
  {
   "from": "2026-07-21T14:30Z",
   "to": "2026-07-21T15:00Z",
   "price": 22.575,
   "carbon": 80,
   "score": 77,
   "label": "excellent"
  },
  {
   "from": "2026-07-21T15:00Z",
   "to": "2026-07-21T15:30Z",
   "price": 35.0175,
   "carbon": 87,
   "score": 35,
   "label": "fair"
  },
  {
   "from": "2026-07-21T15:30Z",
   "to": "2026-07-21T16:00Z",
   "price": 36.5295,
   "carbon": 100,
   "score": 27,
   "label": "poor"
  },
  {
   "from": "2026-07-21T16:00Z",
   "to": "2026-07-21T16:30Z",
   "price": 34.2615,
   "carbon": 115,
   "score": 34,
   "label": "poor"
  },
  {
   "from": "2026-07-21T16:30Z",
   "to": "2026-07-21T17:00Z",
   "price": 36.351,
   "carbon": 144,
   "score": 26,
   "label": "poor"
  },
  {
   "from": "2026-07-21T17:00Z",
   "to": "2026-07-21T17:30Z",
   "price": 39.9315,
   "carbon": 168,
   "score": 19,
   "label": "poor"
  },
  {
   "from": "2026-07-21T17:30Z",
   "to": "2026-07-21T18:00Z",
   "price": 41.412,
   "carbon": 185,
   "score": 15,
   "label": "poor"
  },
  {
   "from": "2026-07-21T18:00Z",
   "to": "2026-07-21T18:30Z",
   "price": 31.311,
   "carbon": 227,
   "score": 29,
   "label": "poor"
  },
  {
   "from": "2026-07-21T18:30Z",
   "to": "2026-07-21T19:00Z",
   "price": 31.2165,
   "carbon": 285,
   "score": 30,
   "label": "poor"
  },
  {
   "from": "2026-07-21T19:00Z",
   "to": "2026-07-21T19:30Z",
   "price": 30.786,
   "carbon": 314,
   "score": 31,
   "label": "poor"
  },
  {
   "from": "2026-07-21T19:30Z",
   "to": "2026-07-21T20:00Z",
   "price": 30.6915,
   "carbon": 349,
   "score": 32,
   "label": "poor"
  },
  {
   "from": "2026-07-21T20:00Z",
   "to": "2026-07-21T20:30Z",
   "price": 30.303,
   "carbon": 371,
   "score": 33,
   "label": "poor"
  },
  {
   "from": "2026-07-21T20:30Z",
   "to": "2026-07-21T21:00Z",
   "price": 30.0405,
   "carbon": 376,
   "score": 36,
   "label": "fair"
  },
  {
   "from": "2026-07-21T21:00Z",
   "to": "2026-07-21T21:30Z",
   "price": 30.1035,
   "carbon": 377,
   "score": 30,
   "label": "poor"
  },
  {
   "from": "2026-07-21T21:30Z",
   "to": "2026-07-21T22:00Z",
   "price": 26.1975,
   "carbon": 376,
   "score": 39,
   "label": "fair"
  }
 ]
}